CLiMB/__init__.py
CLiMB/__pycache__/__init__.cpython-310.pyc
CLiMB/core/CLiMB.py
CLiMB/core/KBound.py
CLiMB/core/KBoundRefined.py
CLiMB/core/KBound_old.py
CLiMB/core/__init__.py
CLiMB/core/__pycache__/CLiMB.cpython-310.pyc
CLiMB/core/__pycache__/KBound.cpython-310.pyc
CLiMB/core/__pycache__/KBoundRefined.cpython-310.pyc
CLiMB/core/__pycache__/__init__.cpython-310.pyc
CLiMB/exploratory/DBSCANExploratory.py
CLiMB/exploratory/HDBSCANExploratory.py
CLiMB/exploratory/OPTICSExploratory.py
CLiMB/exploratory/__init__.py
CLiMB/exploratory/__pycache__/DBSCANExploratory.cpython-310.pyc
CLiMB/exploratory/__pycache__/HDBSCANExploratory.cpython-310.pyc
CLiMB/exploratory/__pycache__/OPTICSExploratory.cpython-310.pyc
CLiMB/exploratory/__pycache__/__init__.cpython-310.pyc
CLiMB/utils/__init__.py
CLiMB/utils/util.py
CLiMB/utils/__pycache__/__init__.cpython-310.pyc
CLiMB/utils/__pycache__/util.cpython-310.pyc
climb_astro-0.2.4.dist-info/licenses/LICENSE
climb_astro-0.2.4.dist-info/METADATA
climb_astro-0.2.4.dist-info/WHEEL
climb_astro-0.2.4.dist-info/top_level.txt
climb_astro-0.2.4.dist-info/RECORD
