Metadata-Version: 2.4
Name: climb-astro
Version: 0.2.4
Summary: A versatile two-phase clustering algorithm designed for datasets with both known and exploratory components.
Home-page: https://github.com/LorenzoMonti/CLiMB
Author: Lorenzo Monti
Author-email: Lorenzo Monti <lorenzomonti42@gmail.com>
License-Expression: MIT
Project-URL: Homepage, https://github.com/LorenzoMonti/CLiMB
Project-URL: Repository, https://github.com/LorenzoMonti/CLiMB.git
Project-URL: BugTracker, https://github.com/LorenzoMonti/CLiMB/issues
Classifier: Programming Language :: Python :: 3
Classifier: Operating System :: OS Independent
Classifier: Topic :: Scientific/Engineering :: Artificial Intelligence
Classifier: Topic :: Scientific/Engineering :: Information Analysis
Requires-Python: >=3.7
License-File: LICENSE
Requires-Dist: numpy>=1.19.0
Requires-Dist: matplotlib>=3.3.0
Requires-Dist: scikit-learn>=0.24.0
Requires-Dist: scipy>=1.6.0
Requires-Dist: pandas>=1.5.3
Requires-Dist: hdbscan>=0.8.27
Provides-Extra: dev
Requires-Dist: pytest>=6.0; extra == "dev"
Requires-Dist: black; extra == "dev"
Requires-Dist: flake8; extra == "dev"
Requires-Dist: sphinx; extra == "dev"
Requires-Dist: sphinx-rtd-theme; extra == "dev"
Dynamic: author
Dynamic: home-page
Dynamic: license-file
Dynamic: requires-python
